plugs_post/__init__.py
plugs_post/admin.py
plugs_post/apps.py
plugs_post/models.py
plugs_post/serializers.py
plugs_post/views.py
plugs_post/migrations/0001_initial.py
plugs_post/migrations/0002_auto_20170913_2144.py
plugs_post/migrations/__init__.py
plugs_post/static/css/plugs_post.css
plugs_post/static/js/plugs_post.js
plugs_post/templates/plugs_post/base.html
plugs_post-0.2.1.dist-info/DESCRIPTION.rst
plugs_post-0.2.1.dist-info/METADATA
plugs_post-0.2.1.dist-info/RECORD
plugs_post-0.2.1.dist-info/WHEEL
plugs_post-0.2.1.dist-info/metadata.json
plugs_post-0.2.1.dist-info/top_level.txt
